d2txt.py
d2txt-0.5.1.dist-info/entry_points.txt
d2txt-0.5.1.dist-info/LICENSE
d2txt-0.5.1.dist-info/WHEEL
d2txt-0.5.1.dist-info/METADATA
d2txt-0.5.1.dist-info/RECORD
