Metadata-Version: 2.1
Name: d2txt
Version: 0.5.1
Summary: Parses Diablo II's TXT files and converts them to TOML files.
Home-page: https://github.com/pastelmind/d2txt
Author: pastelmind
Author-email: keepyourhonor@gmail.com
Requires-Python: >= 3.6
Classifier: Development Status :: 3 - Alpha
Classifier: License :: OSI Approved :: MIT License
Classifier: Operating System :: OS Independent
Classifier: Programming Language :: Python :: 3.6
Classifier: Programming Language :: Python :: 3.7
Classifier: Programming Language :: Python :: 3.8
Classifier: Programming Language :: Python :: 3.9
Requires-Dist: qtoml >= 0.3.0, < 1
Requires-Dist: toml >= 0.10.1, < 1
